thematos/__cli__.py
thematos/__init__.py
thematos/_version.py
thematos/conf/__init__.py
thematos/conf/about/thematos.yaml
thematos/conf/dataset/topic_corpus.yaml
thematos/conf/model/config/lda.yaml
thematos/conf/model/lda.yaml
thematos/conf/model/plot/wordcloud.yaml
thematos/conf/model/summary/topic_train.yaml
thematos/conf/model/topic.yaml
thematos/conf/model/train/topic.yaml
thematos/conf/ngrams/tp_ngrams.yaml
thematos/conf/plot/wordcloud.yaml
thematos/conf/runner/config/infer_topics.yaml
thematos/conf/runner/config/lda.yaml
thematos/conf/runner/topic.yaml
thematos/conf/words/wordprior.yaml
thematos/datasets/__init__.py
thematos/datasets/corpus.py
thematos/datasets/ngrams.py
thematos/models/__init__.py
thematos/models/base.py
thematos/models/config.py
thematos/models/lda.py
thematos/models/prior.py
thematos/models/types.py
thematos/plots/__init__.py
thematos/plots/wordcloud.py
thematos/py.typed
thematos/runners/__init__.py
thematos/runners/config.py
thematos/runners/topic.py
thematos-0.14.5.dist-info/LICENSE
thematos-0.14.5.dist-info/METADATA
thematos-0.14.5.dist-info/WHEEL
thematos-0.14.5.dist-info/entry_points.txt
thematos-0.14.5.dist-info/RECORD
