Metadata-Version: 2.1
Name: thematos
Version: 0.14.5
Summary: A Python Library for Topic Modeling
Home-page: https://thematos.entelecheia.ai
License: MIT
Author: Young Joon Lee
Author-email: entelecheia@hotmail.com
Requires-Python: >=3.9,<3.13
Classifier: License :: OSI Approved :: MIT License
Classifier: Programming Language :: Python :: 3
Classifier: Programming Language :: Python :: 3.9
Classifier: Programming Language :: Python :: 3.10
Classifier: Programming Language :: Python :: 3.11
Classifier: Programming Language :: Python :: 3.12
Requires-Dist: click (>=8.1.3,<9.0.0)
Requires-Dist: hyfi (>=1.36.3,<2.0.0)
Requires-Dist: lexikanon (>=0.6.5,<0.7.0)
Requires-Dist: tomotopy (>=0.13.0,<0.14.0)
Requires-Dist: wordcloud (>=1.9.2,<2.0.0)
Project-URL: Repository, https://github.com/entelecheia/thematos
